django_blog_zinnia-0.20.dist-info/DESCRIPTION.rst
django_blog_zinnia-0.20.dist-info/METADATA
django_blog_zinnia-0.20.dist-info/RECORD
django_blog_zinnia-0.20.dist-info/WHEEL
django_blog_zinnia-0.20.dist-info/metadata.json
django_blog_zinnia-0.20.dist-info/top_level.txt
zinnia/__init__.py
zinnia/apps.py
zinnia/breadcrumbs.py
zinnia/calendar.py
zinnia/comparison.py
zinnia/context.py
zinnia/context_processors.py
zinnia/feeds.py
zinnia/flags.py
zinnia/managers.py
zinnia/markups.py
zinnia/moderator.py
zinnia/ping.py
zinnia/preview.py
zinnia/search.py
zinnia/settings.py
zinnia/signals.py
zinnia/sitemaps.py
zinnia/templating.py
zinnia/admin/__init__.py
zinnia/admin/category.py
zinnia/admin/entry.py
zinnia/admin/fields.py
zinnia/admin/filters.py
zinnia/admin/forms.py
zinnia/admin/widgets.py
zinnia/fixtures/helloworld.json
zinnia/locale/bg/LC_MESSAGES/django.mo
zinnia/locale/bg/LC_MESSAGES/django.po
zinnia/locale/ca/LC_MESSAGES/django.mo
zinnia/locale/ca/LC_MESSAGES/django.po
zinnia/locale/cs/LC_MESSAGES/django.mo
zinnia/locale/cs/LC_MESSAGES/django.po
zinnia/locale/de/LC_MESSAGES/django.mo
zinnia/locale/de/LC_MESSAGES/django.po
zinnia/locale/es/LC_MESSAGES/django.mo
zinnia/locale/es/LC_MESSAGES/django.po
zinnia/locale/eu/LC_MESSAGES/django.mo
zinnia/locale/eu/LC_MESSAGES/django.po
zinnia/locale/fa_IR/LC_MESSAGES/django.mo
zinnia/locale/fa_IR/LC_MESSAGES/django.po
zinnia/locale/fi_FI/LC_MESSAGES/django.mo
zinnia/locale/fi_FI/LC_MESSAGES/django.po
zinnia/locale/fr/LC_MESSAGES/django.mo
zinnia/locale/fr/LC_MESSAGES/django.po
zinnia/locale/he/LC_MESSAGES/django.mo
zinnia/locale/he/LC_MESSAGES/django.po
zinnia/locale/hr_HR/LC_MESSAGES/django.mo
zinnia/locale/hr_HR/LC_MESSAGES/django.po
zinnia/locale/hu/LC_MESSAGES/django.mo
zinnia/locale/hu/LC_MESSAGES/django.po
zinnia/locale/is/LC_MESSAGES/django.mo
zinnia/locale/is/LC_MESSAGES/django.po
zinnia/locale/it/LC_MESSAGES/django.mo
zinnia/locale/it/LC_MESSAGES/django.po
zinnia/locale/lt/LC_MESSAGES/django.mo
zinnia/locale/lt/LC_MESSAGES/django.po
zinnia/locale/nl/LC_MESSAGES/django.mo
zinnia/locale/nl/LC_MESSAGES/django.po
zinnia/locale/pl/LC_MESSAGES/django.mo
zinnia/locale/pl/LC_MESSAGES/django.po
