Metadata-Version: 1.1
Name: django-blog-zinnia
Version: 0.20
Summary: A clear and powerful weblog application powered with Django
Home-page: https://github.com/Fantomas42/django-blog-zinnia
Author: Fantomas42
Author-email: fantomas42@gmail.com
License: BSD License
Keywords: django,blog,weblog,zinnia,post,news
Platform: UNKNOWN
Classifier: Framework :: Django
Classifier: Development Status :: 5 - Production/Stable
Classifier: Environment :: Web Environment
Classifier: Programming Language :: Python :: 2.7
Classifier: Programming Language :: Python :: 3
Classifier: Intended Audience :: Developers
Classifier: Operating System :: OS Independent
Classifier: License :: OSI Approved :: BSD License
Classifier: Topic :: Software Development :: Libraries :: Python Modules
